sdk/__init__.py
sdk/endpoints.py
sdk/sdk.py
lotr_onexyz1-0.1.0.dist-info/METADATA
lotr_onexyz1-0.1.0.dist-info/WHEEL
lotr_onexyz1-0.1.0.dist-info/top_level.txt
lotr_onexyz1-0.1.0.dist-info/RECORD
