Metadata-Version: 2.1
Name: lotr-onexyz1
Version: 0.1.0
Summary: LOTR coding test
Author: Alex
Author-email: 
Requires-Python: >=3.10.9
Requires-Dist: requests
